evinai_health_indices/__init__.py
evinai_health_indices/health_indices.py
evinai_health_indices-0.0.2.dist-info/METADATA
evinai_health_indices-0.0.2.dist-info/WHEEL
evinai_health_indices-0.0.2.dist-info/RECORD
