Metadata-Version: 2.1
Name: evinai-health-indices
Version: 0.0.2
Summary: a unified collection of health indices and indicators eg bmi, bai, etc
Home-page: https://github.com/evinai/evinai-health-indices
License: MIT
Keywords: health-indices,health-indicators,bmi,bodymassindex,bai,birth-rate
Author: evinai
Author-email: togay.tunca@gmail.comm
Requires-Python: >=3.10,<4.0
Classifier: License :: OSI Approved :: MIT License
Classifier: Programming Language :: Python :: 3
Classifier: Programming Language :: Python :: 3.10
Classifier: Programming Language :: Python :: 3.11
Project-URL: Repository, https://github.com/evinai/evinai-health-indices
